doer/doer.py
doer_test_package-0.2.1.dist-info/METADATA
doer_test_package-0.2.1.dist-info/WHEEL
doer_test_package-0.2.1.dist-info/top_level.txt
doer_test_package-0.2.1.dist-info/RECORD
