Metadata-Version: 2.4
Name: doer-test-package
Version: 0.2.1
Summary: Add your description here
Author: rainerBoss
Requires-Python: >=3.10
Requires-Dist: numpy>=2.2.6
